[{"Pos":1,"Team Name":"Quatermass Motorsport","Driver 1":"Jack Pittas","Driver 2":"Harry Langford","Driver 3":"Oliver Forsström2","Fuji":50,"RBull":60,"Spa":87,"Total":197},{"Pos":2,"Team Name":"Mission R 'Powered By Mauds'","Driver 1":"Samy Ariba","Driver 2":"George Stone","Driver 3":"Matuesz Smolny","Fuji":61,"RBull":61,"Spa":65,"Total":187},{"Pos":3,"Team Name":"Sorrento Motorsports","Driver 1":"Kyle Griffiths","Driver 2":"Dominik Pester","Driver 3":"Lukasz Sidor","Fuji":64,"RBull":63,"Spa":53,"Total":180},{"Pos":4,"Team Name":"Crest Autosport Porsche","Driver 1":"Nigel Stock","Driver 2":"Alain McKane","Driver 3":"","Fuji":60,"RBull":58,"Spa":60,"Total":178},{"Pos":5,"Team Name":"Mission R","Driver 1":"Jonathan Berry","Driver 2":"Stijn Weytens","Driver 3":"brandon vincent-squibb","Fuji":70,"RBull":23,"Spa":82,"Total":175},{"Pos":6,"Team Name":"CSA (Team Woza)","Driver 1":"Stephan Wessels","Driver 2":"Jeffrey Kruger","Driver 3":"Jason Raaff","Fuji":22,"RBull":66,"Spa":87,"Total":175},{"Pos":7,"Team Name":"Clark St. James Motorsport Blue","Driver 1":"Craig Corish","Driver 2":"Seany Clark","Driver 3":"Andy White","Fuji":41,"RBull":47,"Spa":65,"Total":153},{"Pos":8,"Team Name":"Crest Autosport BMW","Driver 1":"Stephen Fry","Driver 2":"Steven De Greveleer","Driver 3":"","Fuji":42,"RBull":51,"Spa":30,"Total":123},{"Pos":9,"Team Name":"Ecurie Col d'Oiseaux UK","Driver 1":"Paul Williams","Driver 2":"Mark Baker","Driver 3":"Brandon Schmidt","Fuji":57,"RBull":13,"Spa":40,"Total":110},{"Pos":10,"Team Name":"Mission R 'Backed by Alien Mods'","Driver 1":"Zara Mcguinness","Driver 2":"Keiran Davidson","Driver 3":"Ryan Blackie","Fuji":25,"RBull":36,"Spa":45,"Total":106},{"Pos":11,"Team Name":"Mission R 'Capture Athletics'","Driver 1":"Adam Wilson Weir","Driver 2":"Rob Savage","Driver 3":"Josh Downing","Fuji":25,"RBull":51,"Spa":26,"Total":102},{"Pos":12,"Team Name":"NXTGEN Pink","Driver 1":"Jamie Dorey","Driver 2":"Gavan Gardener","Driver 3":"Mark Sykes","Fuji":43,"RBull":46,"Spa":6,"Total":95},{"Pos":13,"Team Name":"CSA (Team Izzit)","Driver 1":"Wesley Lewin","Driver 2":"Shaun Schutte","Driver 3":"Elwyn Sykes","Fuji":30,"RBull":42,"Spa":18,"Total":90},{"Pos":14,"Team Name":"Ecurie Col d'Oiseaux GER","Driver 1":"Mike Riedner","Driver 2":"Jochen Siegert","Driver 3":"Dirk Wagner","Fuji":38,"RBull":5,"Spa":43,"Total":86},{"Pos":15,"Team Name":"Clark St. James Motorsport Red","Driver 1":"Harry Hartley-Price","Driver 2":"Tim Reid","Driver 3":"","Fuji":31,"RBull":8,"Spa":15,"Total":54},{"Pos":16,"Team Name":"CSA (Team Pasop)","Driver 1":"Davide Favo","Driver 2":"Jopie Seimons","Driver 3":"","Fuji":23,"RBull":25,"Spa":4,"Total":52},{"Pos":17,"Team Name":"Azz Tech Racing","Driver 1":"Gabriel Papaconstantinou","Driver 2":"Jake Pitt","Driver 3":"Matt Cheverton","Fuji":19,"RBull":0,"Spa":0,"Total":19}]