[
   {
        "round_no": 1,
        "track_name": "1-Catalunya",
        "sessions" : [
            {
               "session_no":1, 
               "event_type": "Race 1",
                "subsession_id": 70297109,
                "scored_events" : [
                    {
                        "score_event": "Qualifying",
                        "simsession_name": "QUALIFY", 
                        "scoring_system": 0
                    },
                    {
                        "score_event": "Fastest Lap",
                        "simsession_name": "RACE",
                        "scoring_system": 1            
                    },
                    {
                        "score_event": "Race",
                        "simsession_name": "RACE",
                        "scoring_system": 2         
                    }
                ]
            },{
                "session_no": 2,
                "event_type": "Race 2",
                "subsession_id": 70299051,
                "scored_events" : [
                    {
                        "score_event": "Fastest Lap",
                        "simsession_name": "RACE",
                        "scoring_system": 1            
                    },
                    {
                        "score_event": "Race",
                        "simsession_name": "RACE",
                        "scoring_system": 2         
                    }
                ]
            },{
               "session_no": 3,
               "event_type": "Race 3",
               "subsession_id": 70299903,
               "scored_events" : [
                   {
                       "score_event": "Fastest Lap",
                       "simsession_name": "RACE",
                       "scoring_system": 1            
                   },
                   {
                       "score_event": "Race",
                       "simsession_name": "RACE",
                       "scoring_system": 2         
                   }
               ]
           }
        ]    
   },{
      "round_no": 2,
      "track_name": "2-dunno",
      "sessions" : [
          {
             "session_no":1, 
             "event_type": "Race 1",
              "subsession_id": 70447893,
              "scored_events" : [
                  {
                      "score_event": "Qualifying",
                      "simsession_name": "QUALIFY", 
                      "scoring_system": 0
                  },
                  {
                      "score_event": "Fastest Lap",
                      "simsession_name": "RACE",
                      "scoring_system": 1            
                  },
                  {
                      "score_event": "Race",
                      "simsession_name": "RACE",
                      "scoring_system": 2         
                  }
              ]
          },{
              "session_no": 2,
              "event_type": "Race 2",
              "subsession_id": 70449815,
              "scored_events" : [
                  {
                      "score_event": "Fastest Lap",
                      "simsession_name": "RACE",
                      "scoring_system": 1            
                  },
                  {
                      "score_event": "Race",
                      "simsession_name": "RACE",
                      "scoring_system": 2         
                  }
              ]
          },{
             "session_no": 3,
             "event_type": "Race 3",
             "subsession_id": 70450549,
             "scored_events" : [
                 {
                     "score_event": "Fastest Lap",
                     "simsession_name": "RACE",
                     "scoring_system": 1            
                 },
                 {
                     "score_event": "Race",
                     "simsession_name": "RACE",
                     "scoring_system": 2         
                 }
             ]
         }
      ]    
 }  
]