[[{"Pos":1,"Name":"Dominik Pester","Fuji":37,"RBull":41,"Spa":45,"Imola":39,"Drop":-37,"Penalties":0,"Total":125,"ID":1134363},{"Pos":2,"Name":"Stephan Wessels","Fuji":3,"RBull":33,"Spa":52,"Imola":26,"Drop":-3,"Penalties":0,"Total":111,"ID":684107},{"Pos":3,"Name":"Benjamin Mccluskey","Fuji":41,"RBull":32,"Spa":4,"Imola":30,"Drop":-4,"Penalties":0,"Total":103,"ID":807048},{"Pos":4,"Name":"Harry Langford ","Fuji":0,"RBull":31,"Spa":25,"Imola":35,"Drop":0,"Penalties":0,"Total":91,"ID":856565},{"Pos":5,"Name":"Jack Pittas","Fuji":25,"RBull":16,"Spa":35,"Imola":25,"Drop":-16,"Penalties":0,"Total":85,"ID":880131},{"Pos":6,"Name":"Brandon Schmidt3","Fuji":33,"RBull":0,"Spa":40,"Imola":0,"Drop":0,"Penalties":0,"Total":73,"ID":969021},{"Pos":7,"Name":"Łukasz Sidor","Fuji":19,"RBull":22,"Spa":8,"Imola":21,"Drop":-8,"Penalties":0,"Total":62,"ID":669636},{"Pos":8,"Name":"Gareth Williams7","Fuji":13,"RBull":22,"Spa":20,"Imola":13,"Drop":-13,"Penalties":0,"Total":55,"ID":436196},{"Pos":9,"Name":"Kyle Griffiths","Fuji":27,"RBull":0,"Spa":0,"Imola":27,"Drop":0,"Penalties":0,"Total":54,"ID":720188},{"Pos":10,"Name":"Gabriel Rup","Fuji":0,"RBull":0,"Spa":30,"Imola":22,"Drop":0,"Penalties":0,"Total":52,"ID":1113772},{"Pos":11,"Name":"Gavan Gardener","Fuji":0,"RBull":28,"Spa":0,"Imola":20,"Drop":0,"Penalties":0,"Total":48,"ID":158246},{"Pos":12,"Name":"Jamie Dorey","Fuji":19,"RBull":18,"Spa":6,"Imola":11,"Drop":-6,"Penalties":0,"Total":48,"ID":417499},{"Pos":13,"Name":"Adam Wilson-Weir","Fuji":15,"RBull":17,"Spa":0,"Imola":10,"Drop":0,"Penalties":0,"Total":42,"ID":1095068},{"Pos":14,"Name":"Craign Corish","Fuji":6,"RBull":9,"Spa":13,"Imola":0,"Drop":0,"Penalties":0,"Total":28,"ID":813575},{"Pos":15,"Name":"Wayne Douglas","Fuji":0,"RBull":23,"Spa":0,"Imola":0,"Drop":0,"Penalties":0,"Total":23,"ID":23406},{"Pos":16,"Name":"Jake Pitt","Fuji":0,"RBull":0,"Spa":0,"Imola":21,"Drop":0,"Penalties":0,"Total":21,"ID":361745},{"Pos":17,"Name":"Shaun F Schutte","Fuji":13,"RBull":5,"Spa":2,"Imola":0,"Drop":0,"Penalties":0,"Total":20,"ID":717473},{"Pos":18,"Name":"Keiran Davidson","Fuji":18,"RBull":0,"Spa":0,"Imola":0,"Drop":0,"Penalties":0,"Total":18,"ID":1171274},{"Pos":19,"Name":"Jean McCluan","Fuji":0,"RBull":0,"Spa":0,"Imola":0,"Drop":0,"Penalties":0,"Total":0,"ID":342625},{"Pos":20,"Name":"Harry Hartley-Price","Fuji":21,"RBull":8,"Spa":15,"Imola":6,"Drop":-6,"Penalties":-50,"Total":-6,"ID":884532},{"Pos":21,"Name":"Ben Altria","Fuji":16,"RBull":4,"Spa":10,"Imola":0,"Drop":0,"Penalties":-50,"Total":-20,"ID":876012}],[{"Pos":1,"Name":"brandon vincent-squibb","Fuji":40,"RBull":15,"Spa":47,"Imola":36,"Drop":-15,"Penalties":0,"Total":123,"ID":1016431},{"Pos":2,"Name":"Jeffrey Kruger","Fuji":30,"RBull":0,"Spa":40,"Imola":38,"Drop":0,"Penalties":0,"Total":108,"ID":98121},{"Pos":3,"Name":"Alain McKane","Fuji":35,"RBull":35,"Spa":15,"Imola":12,"Drop":-12,"Penalties":0,"Total":85,"ID":181524},{"Pos":4,"Name":"Nigel Stock","Fuji":23,"RBull":22,"Spa":35,"Imola":6,"Drop":-6,"Penalties":0,"Total":80,"ID":395972},{"Pos":5,"Name":"Jason Raaff","Fuji":11,"RBull":33,"Spa":30,"Imola":10,"Drop":-10,"Penalties":0,"Total":74,"ID":1069108},{"Pos":6,"Name":"Phil McDougall","Fuji":8,"RBull":31,"Spa":2,"Imola":30,"Drop":-2,"Penalties":0,"Total":69,"ID":286267},{"Pos":7,"Name":"Stephen Fry","Fuji":17,"RBull":23,"Spa":25,"Imola":17,"Drop":-17,"Penalties":0,"Total":65,"ID":581527},{"Pos":8,"Name":"Mathew Addy","Fuji":16,"RBull":22,"Spa":10,"Imola":20,"Drop":-10,"Penalties":0,"Total":58,"ID":293575},{"Pos":9,"Name":"Wojciech Kurp","Fuji":0,"RBull":19,"Spa":20,"Imola":17,"Drop":0,"Penalties":0,"Total":56,"ID":1117180},{"Pos":10,"Name":"Matthew Cheverton","Fuji":15,"RBull":0,"Spa":0,"Imola":35,"Drop":0,"Penalties":0,"Total":50,"ID":846950},{"Pos":11,"Name":"Wesley Lewin","Fuji":10,"RBull":21,"Spa":6,"Imola":17,"Drop":-6,"Penalties":0,"Total":48,"ID":888953},{"Pos":12,"Name":"Andy D White","Fuji":20,"RBull":28,"Spa":50,"Imola":9,"Drop":-9,"Penalties":-50,"Total":48,"ID":384854},{"Pos":13,"Name":"George Stone6","Fuji":24,"RBull":14,"Spa":0,"Imola":8,"Drop":0,"Penalties":0,"Total":46,"ID":1117870},{"Pos":14,"Name":"Mark Baker7","Fuji":23,"RBull":4,"Spa":0,"Imola":17,"Drop":0,"Penalties":0,"Total":44,"ID":214278},{"Pos":15,"Name":"Mateusz Smolny","Fuji":0,"RBull":20,"Spa":13,"Imola":0,"Drop":0,"Penalties":0,"Total":33,"ID":1110456},{"Pos":16,"Name":"Ryan Blackie","Fuji":6,"RBull":7,"Spa":0,"Imola":15,"Drop":0,"Penalties":0,"Total":28,"ID":568604},{"Pos":17,"Name":"Jopie Seimons","Fuji":2,"RBull":8,"Spa":0,"Imola":13,"Drop":0,"Penalties":0,"Total":23,"ID":875926},{"Pos":18,"Name":"Paul N T Williams","Fuji":7,"RBull":4,"Spa":0,"Imola":8,"Drop":0,"Penalties":0,"Total":19,"ID":532447},{"Pos":19,"Name":"Mike Riedner","Fuji":0,"RBull":0,"Spa":8,"Imola":2,"Drop":0,"Penalties":0,"Total":10,"ID":34483},{"Pos":20,"Name":"Tim Reid","Fuji":8,"RBull":0,"Spa":0,"Imola":0,"Drop":0,"Penalties":0,"Total":8,"ID":968157}],[{"Pos":1,"Name":"Oliver Forsström2","Fuji":25,"RBull":35,"Spa":52,"Imola":16,"Drop":-16,"Penalties":0,"Total":112,"ID":1185490},{"Pos":2,"Name":"Stijn Weytens","Fuji":30,"RBull":4,"Spa":40,"Imola":23,"Drop":-4,"Penalties":0,"Total":93,"ID":1090079},{"Pos":3,"Name":"Robert Savage 3","Fuji":10,"RBull":39,"Spa":25,"Imola":28,"Drop":-10,"Penalties":0,"Total":92,"ID":1077088},{"Pos":4,"Name":"Samy Ariba","Fuji":36,"RBull":20,"Spa":30,"Imola":23,"Drop":-20,"Penalties":0,"Total":89,"ID":869824},{"Pos":5,"Name":"Zara McGuinness","Fuji":0,"RBull":28,"Spa":45,"Imola":8,"Drop":0,"Penalties":0,"Total":81,"ID":1139680},{"Pos":6,"Name":"Steven De Greveleer","Fuji":23,"RBull":31,"Spa":0,"Imola":24,"Drop":0,"Penalties":0,"Total":78,"ID":712518},{"Pos":7,"Name":"Elwyn Sykes ","Fuji":17,"RBull":22,"Spa":10,"Imola":26,"Drop":-10,"Penalties":0,"Total":65,"ID":645127},{"Pos":8,"Name":"Davide Favo","Fuji":20,"RBull":18,"Spa":6,"Imola":27,"Drop":-6,"Penalties":0,"Total":65,"ID":450627},{"Pos":9,"Name":"Jochen Siegert","Fuji":22,"RBull":0,"Spa":35,"Imola":2,"Drop":0,"Penalties":0,"Total":59,"ID":435038},{"Pos":10,"Name":"Mark Sykes","Fuji":25,"RBull":10,"Spa":0,"Imola":21,"Drop":0,"Penalties":0,"Total":56,"ID":375113},{"Pos":11,"Name":"Jonathan berry2","Fuji":20,"RBull":6,"Spa":0,"Imola":20,"Drop":0,"Penalties":0,"Total":46,"ID":541161},{"Pos":12,"Name":"Mat Gatter","Fuji":15,"RBull":15,"Spa":13,"Imola":14,"Drop":-13,"Penalties":0,"Total":44,"ID":1115893},{"Pos":13,"Name":"Maciej Kisiel","Fuji":18,"RBull":10,"Spa":0,"Imola":15,"Drop":0,"Penalties":0,"Total":43,"ID":1221492},{"Pos":14,"Name":"Dirk Wagner","Fuji":15,"RBull":4,"Spa":4,"Imola":10,"Drop":-4,"Penalties":0,"Total":29,"ID":19519},{"Pos":15,"Name":"Kurt Vanhoenacker","Fuji":24,"RBull":28,"Spa":15,"Imola":24,"Drop":-15,"Penalties":-50,"Total":26,"ID":425754},{"Pos":16,"Name":"Joshua Downing3","Fuji":0,"RBull":15,"Spa":8,"Imola":0,"Drop":0,"Penalties":0,"Total":23,"ID":1227536},{"Pos":17,"Name":"Fabian Koziołek","Fuji":0,"RBull":0,"Spa":4,"Imola":17,"Drop":0,"Penalties":0,"Total":21,"ID":1221391},{"Pos":18,"Name":"Seany Clark","Fuji":17,"RBull":21,"Spa":20,"Imola":9,"Drop":-9,"Penalties":-50,"Total":8,"ID":710321},{"Pos":19,"Name":"Jarosław Patałuch","Fuji":0,"RBull":0,"Spa":2,"Imola":0,"Drop":0,"Penalties":0,"Total":2,"ID":1136269},{"Pos":20,"Name":"Gabriel Papaconstantinou","Fuji":0,"RBull":0,"Spa":0,"Imola":0,"Drop":0,"Penalties":0,"Total":0,"ID":996524}],[{"Pos":1,"Name":"Ian Manners","Fuji":0,"RBull":25,"Spa":45,"Imola":0,"Drop":0,"Penalties":0,"Total":70,"ID":492984},{"Pos":2,"Name":"Ben Benneyworth2","Fuji":0,"RBull":0,"Spa":52,"Imola":0,"Drop":0,"Penalties":0,"Total":52,"ID":452031},{"Pos":3,"Name":"William Guthrie","Fuji":0,"RBull":0,"Spa":0,"Imola":46,"Drop":0,"Penalties":0,"Total":46,"ID":505814},{"Pos":4,"Name":"Patrick Falconer","Fuji":44,"RBull":0,"Spa":0,"Imola":0,"Drop":0,"Penalties":0,"Total":44,"ID":493157},{"Pos":5,"Name":"JonathanlCollins3 ","Fuji":0,"RBull":0,"Spa":0,"Imola":0,"Drop":0,"Penalties":0,"Total":0,"ID":461979}],[{"Pos":1,"Name":"Dominik Pester","Fuji":37,"RBull":41,"Spa":45,"Imola":39,"Drop":-37,"Penalties":0,"Total":125,"ID":1134363},{"Pos":2,"Name":"brandon vincent-squibb","Fuji":40,"RBull":15,"Spa":47,"Imola":36,"Drop":-15,"Penalties":0,"Total":123,"ID":1016431},{"Pos":3,"Name":"Oliver Forsström2","Fuji":25,"RBull":35,"Spa":52,"Imola":16,"Drop":-16,"Penalties":0,"Total":112,"ID":1185490},{"Pos":4,"Name":"Stephan Wessels","Fuji":3,"RBull":33,"Spa":52,"Imola":26,"Drop":-3,"Penalties":0,"Total":111,"ID":684107},{"Pos":5,"Name":"Jeffrey Kruger","Fuji":30,"RBull":0,"Spa":40,"Imola":38,"Drop":0,"Penalties":0,"Total":108,"ID":98121},{"Pos":6,"Name":"Benjamin Mccluskey","Fuji":41,"RBull":32,"Spa":4,"Imola":30,"Drop":-4,"Penalties":0,"Total":103,"ID":807048},{"Pos":7,"Name":"Stijn Weytens","Fuji":30,"RBull":4,"Spa":40,"Imola":23,"Drop":-4,"Penalties":0,"Total":93,"ID":1090079},{"Pos":8,"Name":"Robert Savage 3","Fuji":10,"RBull":39,"Spa":25,"Imola":28,"Drop":-10,"Penalties":0,"Total":92,"ID":1077088},{"Pos":9,"Name":"Harry Langford ","Fuji":0,"RBull":31,"Spa":25,"Imola":35,"Drop":0,"Penalties":0,"Total":91,"ID":856565},{"Pos":10,"Name":"Samy Ariba","Fuji":36,"RBull":20,"Spa":30,"Imola":23,"Drop":-20,"Penalties":0,"Total":89,"ID":869824},{"Pos":11,"Name":"Alain McKane","Fuji":35,"RBull":35,"Spa":15,"Imola":12,"Drop":-12,"Penalties":0,"Total":85,"ID":181524},{"Pos":12,"Name":"Jack Pittas","Fuji":25,"RBull":16,"Spa":35,"Imola":25,"Drop":-16,"Penalties":0,"Total":85,"ID":880131},{"Pos":13,"Name":"Zara McGuinness","Fuji":0,"RBull":28,"Spa":45,"Imola":8,"Drop":0,"Penalties":0,"Total":81,"ID":1139680},{"Pos":14,"Name":"Nigel Stock","Fuji":23,"RBull":22,"Spa":35,"Imola":6,"Drop":-6,"Penalties":0,"Total":80,"ID":395972},{"Pos":15,"Name":"Steven De Greveleer","Fuji":23,"RBull":31,"Spa":0,"Imola":24,"Drop":0,"Penalties":0,"Total":78,"ID":712518},{"Pos":16,"Name":"Jason Raaff","Fuji":11,"RBull":33,"Spa":30,"Imola":10,"Drop":-10,"Penalties":0,"Total":74,"ID":1069108},{"Pos":17,"Name":"Brandon Schmidt3","Fuji":33,"RBull":0,"Spa":40,"Imola":0,"Drop":0,"Penalties":0,"Total":73,"ID":969021},{"Pos":18,"Name":"Ian Manners","Fuji":0,"RBull":25,"Spa":45,"Imola":0,"Drop":0,"Penalties":0,"Total":70,"ID":492984},{"Pos":19,"Name":"Phil McDougall","Fuji":8,"RBull":31,"Spa":2,"Imola":30,"Drop":-2,"Penalties":0,"Total":69,"ID":286267},{"Pos":20,"Name":"Elwyn Sykes ","Fuji":17,"RBull":22,"Spa":10,"Imola":26,"Drop":-10,"Penalties":0,"Total":65,"ID":645127},{"Pos":21,"Name":"Davide Favo","Fuji":20,"RBull":18,"Spa":6,"Imola":27,"Drop":-6,"Penalties":0,"Total":65,"ID":450627},{"Pos":22,"Name":"Stephen Fry","Fuji":17,"RBull":23,"Spa":25,"Imola":17,"Drop":-17,"Penalties":0,"Total":65,"ID":581527},{"Pos":23,"Name":"Łukasz Sidor","Fuji":19,"RBull":22,"Spa":8,"Imola":21,"Drop":-8,"Penalties":0,"Total":62,"ID":669636},{"Pos":24,"Name":"Jochen Siegert","Fuji":22,"RBull":0,"Spa":35,"Imola":2,"Drop":0,"Penalties":0,"Total":59,"ID":435038},{"Pos":25,"Name":"Mathew Addy","Fuji":16,"RBull":22,"Spa":10,"Imola":20,"Drop":-10,"Penalties":0,"Total":58,"ID":293575},{"Pos":26,"Name":"Mark Sykes","Fuji":25,"RBull":10,"Spa":0,"Imola":21,"Drop":0,"Penalties":0,"Total":56,"ID":375113},{"Pos":27,"Name":"Wojciech Kurp","Fuji":0,"RBull":19,"Spa":20,"Imola":17,"Drop":0,"Penalties":0,"Total":56,"ID":1117180},{"Pos":28,"Name":"Gareth Williams7","Fuji":13,"RBull":22,"Spa":20,"Imola":13,"Drop":-13,"Penalties":0,"Total":55,"ID":436196},{"Pos":29,"Name":"Kyle Griffiths","Fuji":27,"RBull":0,"Spa":0,"Imola":27,"Drop":0,"Penalties":0,"Total":54,"ID":720188},{"Pos":30,"Name":"Ben Benneyworth2","Fuji":0,"RBull":0,"Spa":52,"Imola":0,"Drop":0,"Penalties":0,"Total":52,"ID":452031},{"Pos":31,"Name":"Gabriel Rup","Fuji":0,"RBull":0,"Spa":30,"Imola":22,"Drop":0,"Penalties":0,"Total":52,"ID":1113772},{"Pos":32,"Name":"Matthew Cheverton","Fuji":15,"RBull":0,"Spa":0,"Imola":35,"Drop":0,"Penalties":0,"Total":50,"ID":846950},{"Pos":33,"Name":"Wesley Lewin","Fuji":10,"RBull":21,"Spa":6,"Imola":17,"Drop":-6,"Penalties":0,"Total":48,"ID":888953},{"Pos":34,"Name":"Andy D White","Fuji":20,"RBull":28,"Spa":50,"Imola":9,"Drop":-9,"Penalties":-50,"Total":48,"ID":384854},{"Pos":35,"Name":"Gavan Gardener","Fuji":0,"RBull":28,"Spa":0,"Imola":20,"Drop":0,"Penalties":0,"Total":48,"ID":158246},{"Pos":36,"Name":"Jamie Dorey","Fuji":19,"RBull":18,"Spa":6,"Imola":11,"Drop":-6,"Penalties":0,"Total":48,"ID":417499},{"Pos":37,"Name":"William Guthrie","Fuji":0,"RBull":0,"Spa":0,"Imola":46,"Drop":0,"Penalties":0,"Total":46,"ID":505814},{"Pos":38,"Name":"Jonathan berry2","Fuji":20,"RBull":6,"Spa":0,"Imola":20,"Drop":0,"Penalties":0,"Total":46,"ID":541161},{"Pos":39,"Name":"George Stone6","Fuji":24,"RBull":14,"Spa":0,"Imola":8,"Drop":0,"Penalties":0,"Total":46,"ID":1117870},{"Pos":40,"Name":"Patrick Falconer","Fuji":44,"RBull":0,"Spa":0,"Imola":0,"Drop":0,"Penalties":0,"Total":44,"ID":493157},{"Pos":41,"Name":"Mat Gatter","Fuji":15,"RBull":15,"Spa":13,"Imola":14,"Drop":-13,"Penalties":0,"Total":44,"ID":1115893},{"Pos":42,"Name":"Mark Baker7","Fuji":23,"RBull":4,"Spa":0,"Imola":17,"Drop":0,"Penalties":0,"Total":44,"ID":214278},{"Pos":43,"Name":"Maciej Kisiel","Fuji":18,"RBull":10,"Spa":0,"Imola":15,"Drop":0,"Penalties":0,"Total":43,"ID":1221492},{"Pos":44,"Name":"Adam Wilson-Weir","Fuji":15,"RBull":17,"Spa":0,"Imola":10,"Drop":0,"Penalties":0,"Total":42,"ID":1095068},{"Pos":45,"Name":"Mateusz Smolny","Fuji":0,"RBull":20,"Spa":13,"Imola":0,"Drop":0,"Penalties":0,"Total":33,"ID":1110456},{"Pos":46,"Name":"Dirk Wagner","Fuji":15,"RBull":4,"Spa":4,"Imola":10,"Drop":-4,"Penalties":0,"Total":29,"ID":19519},{"Pos":47,"Name":"Ryan Blackie","Fuji":6,"RBull":7,"Spa":0,"Imola":15,"Drop":0,"Penalties":0,"Total":28,"ID":568604},{"Pos":48,"Name":"Craign Corish","Fuji":6,"RBull":9,"Spa":13,"Imola":0,"Drop":0,"Penalties":0,"Total":28,"ID":813575},{"Pos":49,"Name":"Kurt Vanhoenacker","Fuji":24,"RBull":28,"Spa":15,"Imola":24,"Drop":-15,"Penalties":-50,"Total":26,"ID":425754},{"Pos":50,"Name":"Joshua Downing3","Fuji":0,"RBull":15,"Spa":8,"Imola":0,"Drop":0,"Penalties":0,"Total":23,"ID":1227536},{"Pos":51,"Name":"Jopie Seimons","Fuji":2,"RBull":8,"Spa":0,"Imola":13,"Drop":0,"Penalties":0,"Total":23,"ID":875926},{"Pos":52,"Name":"Wayne Douglas","Fuji":0,"RBull":23,"Spa":0,"Imola":0,"Drop":0,"Penalties":0,"Total":23,"ID":23406},{"Pos":53,"Name":"Fabian Koziołek","Fuji":0,"RBull":0,"Spa":4,"Imola":17,"Drop":0,"Penalties":0,"Total":21,"ID":1221391},{"Pos":54,"Name":"Jake Pitt","Fuji":0,"RBull":0,"Spa":0,"Imola":21,"Drop":0,"Penalties":0,"Total":21,"ID":361745},{"Pos":55,"Name":"Shaun F Schutte","Fuji":13,"RBull":5,"Spa":2,"Imola":0,"Drop":0,"Penalties":0,"Total":20,"ID":717473},{"Pos":56,"Name":"Paul N T Williams","Fuji":7,"RBull":4,"Spa":0,"Imola":8,"Drop":0,"Penalties":0,"Total":19,"ID":532447},{"Pos":57,"Name":"Keiran Davidson","Fuji":18,"RBull":0,"Spa":0,"Imola":0,"Drop":0,"Penalties":0,"Total":18,"ID":1171274},{"Pos":58,"Name":"Mike Riedner","Fuji":0,"RBull":0,"Spa":8,"Imola":2,"Drop":0,"Penalties":0,"Total":10,"ID":34483},{"Pos":59,"Name":"Seany Clark","Fuji":17,"RBull":21,"Spa":20,"Imola":9,"Drop":-9,"Penalties":-50,"Total":8,"ID":710321},{"Pos":60,"Name":"Tim Reid","Fuji":8,"RBull":0,"Spa":0,"Imola":0,"Drop":0,"Penalties":0,"Total":8,"ID":968157},{"Pos":61,"Name":"Jarosław Patałuch","Fuji":0,"RBull":0,"Spa":2,"Imola":0,"Drop":0,"Penalties":0,"Total":2,"ID":1136269},{"Pos":62,"Name":"JonathanlCollins3 ","Fuji":0,"RBull":0,"Spa":0,"Imola":0,"Drop":0,"Penalties":0,"Total":0,"ID":461979},{"Pos":63,"Name":"Gabriel Papaconstantinou","Fuji":0,"RBull":0,"Spa":0,"Imola":0,"Drop":0,"Penalties":0,"Total":0,"ID":996524},{"Pos":64,"Name":"Jean McCluan","Fuji":0,"RBull":0,"Spa":0,"Imola":0,"Drop":0,"Penalties":0,"Total":0,"ID":342625},{"Pos":65,"Name":"Harry Hartley-Price","Fuji":21,"RBull":8,"Spa":15,"Imola":6,"Drop":-6,"Penalties":-50,"Total":-6,"ID":884532},{"Pos":66,"Name":"Ben Altria","Fuji":16,"RBull":4,"Spa":10,"Imola":0,"Drop":0,"Penalties":-50,"Total":-20,"ID":876012}]]